retailcalendar/__init__.py
retailcalendar/cal.py
retailcalendar/cli.py
retailcalendar-0.0.5.dist-info/LICENSE
retailcalendar-0.0.5.dist-info/METADATA
retailcalendar-0.0.5.dist-info/WHEEL
retailcalendar-0.0.5.dist-info/entry_points.txt
retailcalendar-0.0.5.dist-info/top_level.txt
retailcalendar-0.0.5.dist-info/RECORD
