Metadata-Version: 2.1
Name: retailcalendar
Version: 0.0.5
Summary: A package to handle NRF's 454 calendar (Retail Calendar)
Author-email: Thiago Weidman <tw@weidman.com.br>
Project-URL: Homepage, https://github.com/thig0w/454calendar
Project-URL: Bug Tracker, https://github.com/thig0w/454calendar/issues
Classifier: Programming Language :: Python :: 3
Classifier: License :: OSI Approved :: GNU General Public License v3 (GPLv3)
Classifier: Operating System :: OS Independent
Requires-Python: >=3.10
License-File: LICENSE
Requires-Dist: click
Requires-Dist: rich
